LICENSE
MANIFEST.in
README.md
setup.py
cli_modules/__init__.py
cli_modules/app.py
cli_modules/cli.py
cli_modules/utils.py
templates/index.html
templinktool.egg-info/PKG-INFO
templinktool.egg-info/SOURCES.txt
templinktool.egg-info/dependency_links.txt
templinktool.egg-info/entry_points.txt
templinktool.egg-info/requires.txt
templinktool.egg-info/top_level.txt