Metadata-Version: 2.1
Name: templinktool
Version: 1.0.0
Summary: Creates a temporary server to share files
Home-page: https://github.com/sdidd/templinkMaker.git
Author: sdidd
Author-email: sdiddtayade@gmail.com
License: MIT
License-File: LICENSE
Requires-Dist: Flask
Requires-Dist: pyngrok
Requires-Dist: werkzeug
